lib25519/__init__.py
lib25519/_lib.py
lib25519/dh.py
lib25519/sign.py
lib25519-20241004.1.dist-info/LICENSE
lib25519-20241004.1.dist-info/METADATA
lib25519-20241004.1.dist-info/WHEEL
lib25519-20241004.1.dist-info/top_level.txt
lib25519-20241004.1.dist-info/RECORD
