Metadata-Version: 2.2
Name: lib25519
Version: 20241004.1
Summary: Python wrapper around implementation of the X25519 and Ed25519 cryptosystems
Author-email: Jan Mojžíš <jan.mojzis@gmail.com>
License: Creative Commons Legal Code
Requires-Python: >=3.7
License-File: LICENSE
